setup.py
distributions_hkl/Binomialdistribution.py
distributions_hkl/Gaussiandistribution.py
distributions_hkl/Generaldistribution.py
distributions_hkl/__init__.py
distributions_hkl.egg-info/PKG-INFO
distributions_hkl.egg-info/SOURCES.txt
distributions_hkl.egg-info/dependency_links.txt
distributions_hkl.egg-info/not-zip-safe
distributions_hkl.egg-info/top_level.txt