Metadata-Version: 1.0
Name: distributions-hkl
Version: 0.2
Summary: Gaussian distributions package by HKL (mlnd programme)
Home-page: UNKNOWN
Author: Hein Ko Lwin
Author-email: heinko94@gmail.com
License: UNKNOWN
Platform: UNKNOWN
